my_library/__init__.py
my_library/dsend.py
danyal_send-0.1.dist-info/METADATA
danyal_send-0.1.dist-info/WHEEL
danyal_send-0.1.dist-info/top_level.txt
danyal_send-0.1.dist-info/RECORD
