Metadata-Version: 2.1
Name: danyal-send
Version: 0.1
Summary: until testing
Home-page: https://github.com/Danyalss/my_library
Author: Danyal
Author-email: danyalsoltani87@gmail.com
Requires-Dist: requests
